fasmga/__init__.py
fasmga/client.py
fasmga/errors.py
fasmga/url.py
fasmga/utils.py
fasmga.py-1.1.0.dist-info/LICENSE
fasmga.py-1.1.0.dist-info/METADATA
fasmga.py-1.1.0.dist-info/WHEEL
fasmga.py-1.1.0.dist-info/top_level.txt
fasmga.py-1.1.0.dist-info/RECORD
