Metadata-Version: 2.1
Name: fasmga.py
Version: 1.1.0
Summary: A Fasm.ga API wrapper written using asyncio.
Home-page: https://github.com/Vincydotzsh/fasmga.py
Author: Vincy.zsh
Author-email: Vincysuper07@gmail.com
License: UNKNOWN
Platform: UNKNOWN
Classifier: Programming Language :: Python :: 3
Classifier: Operating System :: OS Independent
Requires-Python: >=3.7
License-File: LICENSE
Requires-Dist: aiohttp
